anytop/__init__.py
anytop/accumulate.py
anytop/common.py
anytop/histogram.py
anytop/top.py
anytop-0.3.0.dist-info/DESCRIPTION.rst
anytop-0.3.0.dist-info/entry_points.txt
anytop-0.3.0.dist-info/METADATA
anytop-0.3.0.dist-info/metadata.json
anytop-0.3.0.dist-info/RECORD
anytop-0.3.0.dist-info/top_level.txt
anytop-0.3.0.dist-info/WHEEL
