Metadata-Version: 2.0
Name: anytop
Version: 0.3.0
Summary: Streaming frequency distribution viewer.
Home-page: http://github.com/larsyencken/anytop
Author: Lars Yencken
Author-email: lars@yencken.org
License: ISC
Platform: UNKNOWN
Classifier: Development Status :: 2 - Pre-Alpha
Classifier: Intended Audience :: Developers
Classifier: License :: OSI Approved :: BSD License
Classifier: Natural Language :: English
Classifier: Programming Language :: Python :: 2
Classifier: Programming Language :: Python :: 2.7
Classifier: Programming Language :: Python :: 3
Classifier: Programming Language :: Python :: 3.3
Classifier: Programming Language :: Python :: 3.4
Requires-Dist: click (>=3.3)
